pycookiecheat/__init__.py
pycookiecheat/__main__.py
pycookiecheat/chrome.py
pycookiecheat/common.py
pycookiecheat/firefox.py
pycookiecheat-0.8.0.dist-info/AUTHORS.md
pycookiecheat-0.8.0.dist-info/LICENSE
pycookiecheat-0.8.0.dist-info/METADATA
pycookiecheat-0.8.0.dist-info/WHEEL
pycookiecheat-0.8.0.dist-info/entry_points.txt
pycookiecheat-0.8.0.dist-info/top_level.txt
pycookiecheat-0.8.0.dist-info/RECORD
