Metadata-Version: 2.1
Name: pycookiecheat
Version: 0.8.0
Summary: Borrow cookies from your browser's authenticated session for use in Python scripts.
Author-email: Nathan Henrie <nate@n8henrie.com>
License: MIT
Project-URL: homepage, https://github.com/n8henrie/pycookiecheat
Keywords: pycookiecheat,chrome,chromium cookies,cookies,firefox
Classifier: Natural Language :: English
Classifier: Programming Language :: Python :: 3
Classifier: Programming Language :: Python :: 3.9
Classifier: Programming Language :: Python :: 3.10
Classifier: Programming Language :: Python :: 3.11
Classifier: Programming Language :: Python :: 3.12
Classifier: Programming Language :: Python :: 3.13
License-File: LICENSE
License-File: AUTHORS.md
Requires-Dist: cryptography==43.*
Requires-Dist: keyring==25.*
Provides-Extra: test
Requires-Dist: mypy==1.*; extra == "test"
Requires-Dist: playwright==1.*; extra == "test"
Requires-Dist: pytest==8.*; extra == "test"
Requires-Dist: ruff==0.7.*; extra == "test"
Requires-Dist: tox==4.*; extra == "test"
Provides-Extra: dev
Requires-Dist: build==1.*; extra == "dev"
Requires-Dist: twine==5.*; extra == "dev"
Requires-Dist: wheel==0.43.*; extra == "dev"
